dxbench/__init__.py
dxbench/bot.py
dxbench/registry.py
dxbench/runner.py
dxbench/test.py
dxbench/cut/__init__.py
dxbench/cut/add.py
dxbench/internal/__init__.py
dxbench/internal/generation.py
dxbench/internal/metrics.py
dxbench/internal/prompts.py
dxbench/internal/sandbox.py
dxbench-0.0.0.dist-info/licenses/LICENSE.md
dxbench-0.0.0.dist-info/METADATA
dxbench-0.0.0.dist-info/WHEEL
dxbench-0.0.0.dist-info/top_level.txt
dxbench-0.0.0.dist-info/RECORD
