Metadata-Version: 2.4
Name: dxbench
Version: 0.0.0
Summary: Evaluation for LLMs on developer experience.
Author-email: BriHan <brihan.tech@gmail.com>
License: MIT
Project-URL: homepage, https://dxbench.org
Classifier: Development Status :: 3 - Alpha
Classifier: Intended Audience :: Developers
Classifier: License :: OSI Approved :: MIT License
Classifier: Programming Language :: Python :: 3
Requires-Python: >=3.10
License-File: LICENSE.md
Requires-Dist: docker==7.1.0
Requires-Dist: platformdirs==4.3.8
Provides-Extra: dev
Requires-Dist: black==25.1.0; extra == "dev"
Requires-Dist: flake8==7.3.0; extra == "dev"
Requires-Dist: flake8-import-order==0.19.2; extra == "dev"
Requires-Dist: platformdirs==4.3.8; extra == "dev"
Requires-Dist: pytest==8.3.3; extra == "dev"
Requires-Dist: docker==7.1.0; extra == "dev"
Provides-Extra: publish
Requires-Dist: build==1.3.0; extra == "publish"
Requires-Dist: twine==6.1.0; extra == "publish"
Dynamic: license-file
